gollm/__init__.py
gollm/__main__.py
gollm/cli.py
gollm/main.py
gollm/cli/__init__.py
gollm/cli/commands/__init__.py
gollm/cli/commands/config.py
gollm/cli/commands/direct.py
gollm/cli/commands/generate.py
gollm/cli/commands/project.py
gollm/cli/commands/validate.py
gollm/cli/utils/__init__.py
gollm/cli/utils/file_handling.py
gollm/cli/utils/formatting.py
gollm/commands/__init__.py
gollm/commands/direct.py
gollm/config/__init__.py
gollm/config/aggregator.py
gollm/config/config.py
gollm/config/parsers.py
gollm/core/session_manager.py
gollm/core/session_models.py
gollm/git/__init__.py
gollm/git/analyzer.py
gollm/git/hooks.py
gollm/ide/__init__.py
gollm/ide/file_watcher.py
gollm/ide/language_server.py
gollm/ide/vscode_extension.py
gollm/llm/__init__.py
gollm/llm/context_builder.py
gollm/llm/direct_api.py
gollm/llm/ollama_adapter.py
gollm/llm/orchestrator.py
gollm/llm/prompt_formatter.py
gollm/llm/provider_manager.py
gollm/llm/response_validator.py
gollm/llm/orchestrator/__init__.py
gollm/llm/orchestrator/llm_client.py
gollm/llm/orchestrator/models.py
gollm/llm/orchestrator/orchestrator.py
gollm/llm/orchestrator/response_validator.py
gollm/llm/providers/__init__.py
gollm/llm/providers/base.py
gollm/llm/providers/config.py
gollm/llm/providers/anthropic/__init__.py
gollm/llm/providers/anthropic/provider.py
gollm/llm/providers/ollama/__init__.py
gollm/llm/providers/ollama/adapter.py
gollm/llm/providers/ollama/benchmark.py
gollm/llm/providers/ollama/config.py
gollm/llm/providers/ollama/factory.py
gollm/llm/providers/ollama/generation.py
gollm/llm/providers/ollama/health.py
gollm/llm/providers/ollama/http_client.py
gollm/llm/providers/ollama/init_new.py
gollm/llm/providers/ollama/migrate.py
gollm/llm/providers/ollama/migration.py
gollm/llm/providers/ollama/models.py
gollm/llm/providers/ollama/modular_adapter.py
gollm/llm/providers/ollama/prompt.py
gollm/llm/providers/ollama/provider.py
gollm/llm/providers/ollama/provider_new.py
gollm/llm/providers/ollama/grpc/__init__.py
gollm-0.1.27.dist-info/licenses/LICENSE
gollm-0.1.27.dist-info/METADATA
gollm-0.1.27.dist-info/WHEEL
gollm-0.1.27.dist-info/entry_points.txt
gollm-0.1.27.dist-info/top_level.txt
gollm-0.1.27.dist-info/RECORD
