Metadata-Version: 2.4
Name: gollm
Version: 0.1.27
Summary: Go Learn, Lead, Master! - Inteligentny system kontroli jakości kodu z integracją LLM
Home-page: https://github.com/wronai/gollm
Author: Tom Sapletta
Author-email: Tom Sapletta <info@softreck.dev>
License: Apache-2.0
Keywords: code-quality,linting,llm,python,automation
Classifier: Development Status :: 3 - Alpha
Classifier: Intended Audience :: Developers
Classifier: License :: OSI Approved :: MIT License
Classifier: Programming Language :: Python :: 3
Classifier: Programming Language :: Python :: 3.9
Classifier: Programming Language :: Python :: 3.10
Classifier: Programming Language :: Python :: 3.11
Classifier: Topic :: Software Development :: Quality Assurance
Classifier: Topic :: Software Development :: Libraries :: Python Modules
Requires-Python: >=3.8.1
License-File: LICENSE
Requires-Dist: click>=8.0.0
Requires-Dist: pyyaml>=6.0
Requires-Dist: toml>=0.10.0
Requires-Dist: psutil>=5.0.0
Requires-Dist: aiofiles>=0.8.0
Requires-Dist: pydantic>=1.10.0
Requires-Dist: aiohttp>=3.9.0
Provides-Extra: dev
Requires-Dist: pytest>=7.0.0; extra == "dev"
Requires-Dist: pytest-asyncio>=0.21.0; extra == "dev"
Requires-Dist: black>=23.0.0; extra == "dev"
Requires-Dist: flake8>=6.0.0; extra == "dev"
Requires-Dist: mypy>=1.0.0; extra == "dev"
Requires-Dist: coverage>=7.0.0; extra == "dev"
Provides-Extra: llm
Requires-Dist: openai>=1.0.0; extra == "llm"
Requires-Dist: anthropic>=0.3.0; extra == "llm"
Dynamic: author
Dynamic: home-page
Dynamic: license-file
Dynamic: requires-python
